state/__init__.py
state/state.py
pystates3-0.1.4.dist-info/LICENSE.txt
pystates3-0.1.4.dist-info/WHEEL
pystates3-0.1.4.dist-info/METADATA
pystates3-0.1.4.dist-info/RECORD
